numericalAnalysis/__init__.py
numericalAnalysis/analysor.py
numericalAnalysisTool-0.3.0.dist-info/METADATA
numericalAnalysisTool-0.3.0.dist-info/WHEEL
numericalAnalysisTool-0.3.0.dist-info/top_level.txt
numericalAnalysisTool-0.3.0.dist-info/RECORD
