Metadata-Version: 2.1
Name: numericalAnalysisTool
Version: 0.3.0
Summary: Numerical anlysis tool kit
Home-page: https://github.com/CafeKrem/pyNumericalAnlysis
Author: Clément Dutriez
Author-email: clement.dutriez@u-pem.fr
Requires-Python: >=3.6
Requires-Dist: pandas
Requires-Dist: numpy
Requires-Dist: seaborn
Requires-Dist: plotly
